rest_framework_apicontrol/__init__.py
rest_framework_apicontrol/admin.py
rest_framework_apicontrol/apps.py
rest_framework_apicontrol/context_processors.py
rest_framework_apicontrol/migrations/0001_initial.py
rest_framework_apicontrol/migrations/0002_auto_20180328_0152.py
rest_framework_apicontrol/migrations/0003_auto_20180403_0512.py
rest_framework_apicontrol/migrations/0004_auto_20181029_1933.py
rest_framework_apicontrol/migrations/0005_loggingevent_logginggroup.py
rest_framework_apicontrol/migrations/0006_logginggroup_code.py
rest_framework_apicontrol/migrations/0007_create_default_logging_group.py
rest_framework_apicontrol/migrations/0008_loggingevent_logging_group.py
rest_framework_apicontrol/migrations/0009_loggingevent_origin.py
rest_framework_apicontrol/migrations/0010_auto_20201224_2201.py
rest_framework_apicontrol/migrations/0011_auto_20201226_0009.py
rest_framework_apicontrol/migrations/0012_create_default_app.py
rest_framework_apicontrol/migrations/__init__.py
rest_framework_apicontrol/mixins.py
rest_framework_apicontrol/models.py
rest_framework_apicontrol/permissions.py
rest_framework_apicontrol/serializers.py
rest_framework_apicontrol/signals.py
rest_framework_apicontrol/urls.py
rest_framework_apicontrol/utils.py
rest_framework_apicontrol/views.py
rest_framework_apicontrol/wsgi.py
rest_framework_apicontrol-0.8.4.dist-info/LICENSE
rest_framework_apicontrol-0.8.4.dist-info/WHEEL
rest_framework_apicontrol-0.8.4.dist-info/METADATA
rest_framework_apicontrol-0.8.4.dist-info/RECORD
