Metadata-Version: 2.1
Name: rest-framework-apicontrol
Version: 0.8.4
Summary: Control Clients Apps access over REST APIs with ApiKeys
License: MIT
Author: Marcelo Cueto
Author-email: cueto@live.cl
Requires-Python: >3.6
Classifier: Development Status :: 4 - Beta
Classifier: Environment :: Web Environment
Classifier: Framework :: Django
Classifier: Framework :: Django :: 2.2
Classifier: Framework :: Django :: 3.0
Classifier: Framework :: Django :: 3.1
Classifier: Intended Audience :: Developers
Classifier: License :: OSI Approved :: MIT License
Classifier: Operating System :: OS Independent
Classifier: Programming Language :: Python
Classifier: Programming Language :: Python :: 3
Classifier: Programming Language :: Python :: 3.6
Classifier: Programming Language :: Python :: 3.7
Classifier: Programming Language :: Python :: 3.8
Classifier: Programming Language :: Python :: 3.9
Classifier: Topic :: Internet :: WWW/HTTP
Requires-Dist: Django (>2.2)
Requires-Dist: djangorestframework (>3.7.0)
Requires-Dist: psycopg2-binary (>=2.8.2)
